mini_sisso/executor_numpy.py
mini_sisso/executor_torch.py
mini_sisso/feature_generator.py
mini_sisso/model.py
mini_sisso/recipe.py
mini_sisso/regressor_numpy.py
mini_sisso/regressor_torch.py
mini_sisso-1.2.0.dist-info/METADATA
mini_sisso-1.2.0.dist-info/WHEEL
mini_sisso-1.2.0.dist-info/RECORD
