Metadata-Version: 2.4
Name: mini-sisso
Version: 1.2.0
Summary: A lightweight and user-friendly Python implementation of the SISSO algorithm for symbolic regression, compatible with scikit-learn.
Project-URL: Homepage, https://github.com/shinkawa-shuan/mini-sisso
Project-URL: Repository, https://github.com/shinkawa-shuan/mini-sisso
Project-URL: Issues, https://github.com/shinkawa-shuan/mini-sisso/issues
Author-email: shinkawa shuan <s.shuan16@gmail.com>
License-Expression: MIT
Classifier: Development Status :: 4 - Beta
Classifier: Intended Audience :: Science/Research
Classifier: License :: OSI Approved :: MIT License
Classifier: Operating System :: OS Independent
Classifier: Programming Language :: Python :: 3
Classifier: Topic :: Scientific/Engineering :: Artificial Intelligence
Requires-Python: >=3.8
Requires-Dist: dcor>=0.6
Requires-Dist: lightgbm>=3.0.0
Requires-Dist: numpy>=1.20.0
Requires-Dist: pandas>=1.3.0
Requires-Dist: scikit-learn>=1.0.0
Requires-Dist: scipy>=1.7.0
Provides-Extra: gpu
Requires-Dist: torch>=1.9.0; extra == 'gpu'
